gcs_utils_package/__init__.py
gcs_utils_package/funcs.py
gcs_utils_package-0.4.dist-info/METADATA
gcs_utils_package-0.4.dist-info/WHEEL
gcs_utils_package-0.4.dist-info/top_level.txt
gcs_utils_package-0.4.dist-info/RECORD
