Metadata-Version: 2.1
Name: gcs-utils-package
Version: 0.4
Classifier: Programming Language :: Python :: 3.8
Classifier: Programming Language :: Python :: 3.9
Requires-Python: >=3.8.0
Requires-Dist: google-cloud-storage
Requires-Dist: Pillow
